spark_profiling/__init__.py
spark_profiling-0.1.dist-info/METADATA
spark_profiling-0.1.dist-info/WHEEL
spark_profiling-0.1.dist-info/top_level.txt
spark_profiling-0.1.dist-info/RECORD
